odoo/addons/hr_expense_substate/README.rst
odoo/addons/hr_expense_substate/__init__.py
odoo/addons/hr_expense_substate/__manifest__.py
odoo/addons/hr_expense_substate/data/hr_expense_substate_data.xml
odoo/addons/hr_expense_substate/data/hr_expense_substate_mail_template_data.xml
odoo/addons/hr_expense_substate/demo/hr_expense_substate_demo.xml
odoo/addons/hr_expense_substate/i18n/hr_expense_substate.pot
odoo/addons/hr_expense_substate/models/__init__.py
odoo/addons/hr_expense_substate/models/hr_expense.py
odoo/addons/hr_expense_substate/readme/CONTRIBUTORS.rst
odoo/addons/hr_expense_substate/readme/DESCRIPTION.rst
odoo/addons/hr_expense_substate/readme/USAGE.rst
odoo/addons/hr_expense_substate/static/description/icon.png
odoo/addons/hr_expense_substate/static/description/index.html
odoo/addons/hr_expense_substate/views/hr_expense_views.xml
odoo14_addon_hr_expense_substate-14.0.1.0.1.dist-info/METADATA
odoo14_addon_hr_expense_substate-14.0.1.0.1.dist-info/WHEEL
odoo14_addon_hr_expense_substate-14.0.1.0.1.dist-info/top_level.txt
odoo14_addon_hr_expense_substate-14.0.1.0.1.dist-info/RECORD
